Metadata-Version: 1.1
Name: fython
Version: 0.0.2
Summary: Functional utilities for Python, inspired by Scala
Home-page: https://github.com/tsah/fython
Author: Tsah Weiss
Author-email: UNKNOWN
License: MIT
Platform: UNKNOWN
Classifier: Development Status :: 3 - Alpha
Classifier: Intended Audience :: Developers
Classifier: Topic :: Software Development :: Libraries
Classifier: License :: OSI Approved :: MIT License
Classifier: Programming Language :: Python :: 3.7
Classifier: Programming Language :: Python :: 3.8
Classifier: Programming Language :: Python :: 3.9
